{
  "3829174A": " Ganaste 500 fichas",
  "4956201B": "sin premio, prob谩 en la pr贸xima carga",
  "7265830C": "sin premio, prob谩 en la pr贸xima carga",
  "8012937D": "sin premio, prob谩 en la pr贸xima carga",
  "5139702E": "sin premio, prob谩 en la pr贸xima carga",
  "2748905F": "sin premio, prob谩 en la pr贸xima carga",
  "6904728G": "sin premio, prob谩 en la pr贸xima carga",
  "8173059H": "sin premio, prob谩 en la pr贸xima carga",
  "5402186I": "sin premio, prob谩 en la pr贸xima carga",
  "6938051J": "sin premio, prob谩 en la pr贸xima carga",
  "9234710K": " Ganaste 500 fichas",
  "3501928L": "sin premio, prob谩 en la pr贸xima carga",
  "8192634M": "sin premio, prob谩 en la pr贸xima carga",
  "7028351N": "sin premio, prob谩 en la pr贸xima carga",
  "4763109O": "sin premio, prob谩 en la pr贸xima carga",
  "6981032P": "sin premio, prob谩 en la pr贸xima carga",
  "5802964Q": "sin premio, prob谩 en la pr贸xima carga",
  "7905341R": "sin premio, prob谩 en la pr贸xima carga",
  "8902753S": "sin premio, prob谩 en la pr贸xima carga",
  "1095872T": "sin premio, prob谩 en la pr贸xima carga",
  "3258710U": " Ganaste 500 fichas",
  "7902345V": "sin premio, prob谩 en la pr贸xima carga",
  "8926713W": "sin premio, prob谩 en la pr贸xima carga",
  "1359087X": "sin premio, prob谩 en la pr贸xima carga",
  "4681029Y": "sin premio, prob谩 en la pr贸xima carga",
  "2758093Z": "sin premio, prob谩 en la pr贸xima carga",
  "6591802A": "sin premio, prob谩 en la pr贸xima carga",
  "8019264B": "sin premio, prob谩 en la pr贸xima carga",
  "1958073C": "sin premio, prob谩 en la pr贸xima carga",
  "9346180D": " Ganaste 500 fichas",
  "6892305E": "sin premio, prob谩 en la pr贸xima carga",
  "5204819F": "sin premio, prob谩 en la pr贸xima carga",
  "7058923G": "sin premio, prob谩 en la pr贸xima carga",
  "4381590H": "sin premio, prob谩 en la pr贸xima carga",
  "1950648I": "sin premio, prob谩 en la pr贸xima carga",
  "8019527J": "sin premio, prob谩 en la pr贸xima carga",
  "5602983K": "sin premio, prob谩 en la pr贸xima carga",
  "2950761L": "sin premio, prob谩 en la pr贸xima carga",
  "4938105M": "sin premio, prob谩 en la pr贸xima carga",
  "7920516N": " Ganaste 500 fichas",
  "6520918O": "sin premio, prob谩 en la pr贸xima carga",
  "9082317P": "sin premio, prob谩 en la pr贸xima carga",
  "3049825Q": "sin premio, prob谩 en la pr贸xima carga",
  "1790532R": "sin premio, prob谩 en la pr贸xima carga",
  "8569301S": "sin premio, prob谩 en la pr贸xima carga",
  "6908325T": "sin premio, prob谩 en la pr贸xima carga",
  "2396801U": "sin premio, prob谩 en la pr贸xima carga",
  "5263098V": "sin premio, prob谩 en la pr贸xima carga",
  "6920857W": " Ganaste 500 fichas",
  "3089625X": "sin premio, prob谩 en la pr贸xima carga",
  "4196803Y": "sin premio, prob谩 en la pr贸xima carga",
  "9857013Z": "sin premio, prob谩 en la pr贸xima carga",
  "7038921A": "sin premio, prob谩 en la pr贸xima carga",
  "6048925B": "sin premio, prob谩 en la pr贸xima carga",
  "5089736C": "sin premio, prob谩 en la pr贸xima carga",
  "8972504D": "sin premio, prob谩 en la pr贸xima carga",
  "4168029E": " Ganaste 500 fichas",
  "5082917F": "sin premio, prob谩 en la pr贸xima carga",
  "9028165G": "sin premio, prob谩 en la pr贸xima carga",
  "3157802H": "sin premio, prob谩 en la pr贸xima carga",
  "9258016I": "sin premio, prob谩 en la pr贸xima carga",
  "1986237J": "sin premio, prob谩 en la pr贸xima carga",
  "8350194K": "sin premio, prob谩 en la pr贸xima carga",
  "9231507L": "sin premio, prob谩 en la pr贸xima carga",
  "6593018M": "sin premio, prob谩 en la pr贸xima carga",
  "4019826N": " Ganaste 500 fichas",
  "2850937O": "sin premio, prob谩 en la pr贸xima carga",
  "5918023P": "sin premio, prob谩 en la pr贸xima carga",
  "7941802Q": "sin premio, prob谩 en la pr贸xima carga",
  "1205983R": "sin premio, prob谩 en la pr贸xima carga",
  "9572038S": "sin premio, prob谩 en la pr贸xima carga",
  "6791235T": "sin premio, prob谩 en la pr贸xima carga",
  "8305921U": "sin premio, prob谩 en la pr贸xima carga",
  "9051782V": "sin premio, prob谩 en la pr贸xima carga",
  "2485190W": " Ganaste 500 fichas",
  "3709285X": "sin premio, prob谩 en la pr贸xima carga",
  "6823059Y": "sin premio, prob谩 en la pr贸xima carga",
  "9152803Z": "sin premio, prob谩 en la pr贸xima carga",
  "5701928A": "sin premio, prob谩 en la pr贸xima carga",
  "3029581B": "sin premio, prob谩 en la pr贸xima carga",
  "6910538C": "sin premio, prob谩 en la pr贸xima carga",
  "1928053D": "sin premio, prob谩 en la pr贸xima carga",
  "8401926E": "sin premio, prob谩 en la pr贸xima carga",
  "5932081F": " Ganaste 500 fichas",
  "8025913G": "sin premio, prob谩 en la pr贸xima carga",
  "4975102H": "sin premio, prob谩 en la pr贸xima carga",
  "6925813I": "sin premio, prob谩 en la pr贸xima carga",
  "8912057J": "sin premio, prob谩 en la pr贸xima carga",
  "2095184K": "sin premio, prob谩 en la pr贸xima carga",
  "8105923L": "sin premio, prob谩 en la pr贸xima carga",
  "3259801M": "sin premio, prob谩 en la pr贸xima carga",
  "5970132N": "sin premio, prob谩 en la pr贸xima carga",
  "4691850O": " Ganaste 500 fichas",
  "7820593P": "sin premio, prob谩 en la pr贸xima carga",
  "9601258Q": "sin premio, prob谩 en la pr贸xima carga",
  "5309218R": "sin premio, prob谩 en la pr贸xima carga",
  "6890321S": "sin premio, prob谩 en la pr贸xima carga"
}
